[{"hexcode":"#d6ec92","hsl":[75,70,75],"category":"green","tints":["#a9c653","#c1db70","#d6ec92","#e8f7ba","#f8fee7"]},{"hexcode":"#f6e84b","hsl":[55,90,63],"category":"yellow","tints":["#baae21","#e7d727","#f6e84b","#fcf179","#fff8a8"]},{"hexcode":"#545bd3","hsl":[237,59,58],"category":"blue","tints":["#3b3f87","#3e44b6","#545bd3","#757be6","#9b9ff3"]},{"hexcode":"#c90c0e","hsl":[359,89,42],"category":"red","tints":["#5f1113","#921113","#c90c0e","#f81215","#fe3e41"]},{"hexcode":"#f56daa","hsl":[333,87,69],"category":"red","tints":["#d12975","#e7468e","#f56daa","#fa99c5","#fdc9e0"]},{"hexcode":"#78cc53","hsl":[102,54,56],"category":"green","tints":["#4f7b3d","#61a942","#78cc53","#92e071","#b0ef95"]},{"hexcode":"#e8e23d","hsl":[58,79,57],"category":"yellow","tints":["#969227","#cbc525","#e8e23d","#f6f160","#fefb8a"]},{"hexcode":"#280012","hsl":[333,100,8],"category":"brown","tints":["#000000","#130109","#280012","#5c0029","#8f0040"]},{"hexcode":"#169ce1","hsl":[200,82,48],"category":"blue","tints":["#1b5674","#1b78a7","#169ce1","#38b3f0","#64c6f7"]},{"hexcode":"#29e007","hsl":[111,94,45],"category":"green","tints":["#1f6f11","#25a40e","#29e007","#3efc1d","#67ff4d"]},{"hexcode":"#26738f","hsl":[196,58,35],"category":"blue","tints":["#182d35","#214e5e","#26738f","#2597c1","#33b6e6"]},{"hexcode":"#ccb5f6","hsl":[261,78,84],"category":"purple","tints":["#936ed8","#af90ea","#ccb5f6","#d8c5fb","#e5d7ff"]},{"hexcode":"#e7822e","hsl":[27,79,54],"category":"orange","tints":["#8a5224","#be6823","#e7822e","#f59b51","#feb67b"]},{"hexcode":"#9f8d66","hsl":[41,23,51],"category":"orange","tints":["#51504d","#766e5b","#9f8d66","#bca87b","#d5c195"]},{"hexcode":"#f24c88","hsl":[338,86,62],"category":"red","tints":["#b22458","#e2286c","#f24c88","#f778a7","#fba7c6"]},{"hexcode":"#6bb299","hsl":[159,32,56],"category":"green","tints":["#51675f","#5b8f7d","#6bb299","#84cdb3","#a2e2cb"]},{"hexcode":"#53f929","hsl":[108,95,57],"category":"green","tints":["#34a518","#3bde12","#53f929","#7afc59","#a2fe8a"]},{"hexcode":"#a1a2e8","hsl":[239,61,77],"category":"blue","tints":["#6466be","#8081d6","#a1a2e8","#c6c7f5","#f1f1fe"]},{"hexcode":"#cf22c2","hsl":[305,72,47],"category":"purple","tints":["#692163","#99248f","#cf22c2","#eb37dc","#f85deb"]},{"hexcode":"#973f64","hsl":[335,41,42],"category":"red","tints":["#442c36","#6b384d","#973f64","#c3467a","#d96394"]},{"hexcode":"#d9b1c7","hsl":[327,34,77],"category":"red","tints":["#a18293","#bf97ad","#d9b1c7","#eccfdf","#fbf3f8"]},{"hexcode":"#2cf18e","hsl":[150,88,56],"category":"green","tints":["#1d9a5c","#1ad175","#2cf18e","#59f7a8","#88fbc2"]},{"hexcode":"#d9e143","hsl":[63,72,57],"category":"green","tints":["#8b8f2d","#bbc22e","#d9e143","#e9f066","#f5fa8e"]},{"hexcode":"#4a6179","hsl":[211,24,38],"category":"blue","tints":["#2c2e30","#3d4751","#4a6179","#5179a4","#6592c3"]},{"hexcode":"#f4b5b3","hsl":[2,75,83],"category":"red","tints":["#d5706d","#e7908d","#f4b5b3","#fac4c2","#fed4d2"]},{"hexcode":"#954a8d","hsl":[306,34,44],"category":"purple","tints":["#463544","#6c4267","#954a8d","#bd56b3","#d572cb"]},{"hexcode":"#34b192","hsl":[165,55,45],"category":"green","tints":["#29564b","#31816d","#34b192","#42d7b2","#63e9c7"]},{"hexcode":"#05fc53","hsl":[139,98,50],"category":"green","tints":["#118837","#0cc045","#05fc53","#34fe74","#66ff96"]},{"hexcode":"#f4cea5","hsl":[31,78,80],"category":"orange","tints":["#d49b5e","#e7b47e","#f4cea5","#fce6cf","#ffffff"]},{"hexcode":"#9dafd7","hsl":[221,42,73],"category":"blue","tints":["#6d7da2","#8296bf","#9dafd7","#bdcbea","#e2e9f8"]},{"hexcode":"#5934bd","hsl":[256,57,47],"category":"purple","tints":["#392b5e","#4a328b","#5934bd","#6f48db","#8d6aec"]},{"hexcode":"#817141","hsl":[45,33,38],"category":"brown","tints":["#343128","#585037","#817141","#af9546","#cdb05b"]},{"hexcode":"#3ce3fe","hsl":[188,99,62],"category":"blue","tints":["#16a9c0","#18d4f2","#3ce3fe","#71ebfe","#a4f2ff"]},{"hexcode":"#f7aaa4","hsl":[4,84,81],"category":"red","tints":["#db645c","#ec867e","#f7aaa4","#fabcb7","#fdcdc9"]},{"hexcode":"#9727a2","hsl":[295,61,39],"category":"purple","tints":["#411d44","#692470","#9727a2","#c724d6","#dd42eb"]},{"hexcode":"#730b34","hsl":[336,83,25],"category":"red","tints":["#15050b","#420a21","#730b34","#a70c4a","#db0a5e"]},{"hexcode":"#2067e7","hsl":[219,81,52],"category":"blue","tints":["#204383","#1f54b7","#2067e7","#4c85f0","#78a5f7"]},{"hexcode":"#175efe","hsl":[222,99,54],"category":"blue","tints":["#123b9b","#0c48d4","#175efe","#487ffe","#7ba2fe"]},{"hexcode":"#a26f2c","hsl":[34,57,40],"category":"orange","tints":["#463620","#705129","#a26f2c","#d58b2a","#e8a34a"]},{"hexcode":"#9f5dd7","hsl":[272,60,60],"category":"purple","tints":["#693d8f","#8440bf","#9f5dd7","#b67de8","#cfa3f5"]},{"hexcode":"#d05b1f","hsl":[20,74,47],"category":"orange","tints":["#6a3820","#9b4a22","#d05b1f","#ed7335","#fa905c"]},{"hexcode":"#53b693","hsl":[159,40,52],"category":"green","tints":["#416256","#4b8b75","#53b693","#6ecfad","#8de2c4"]},{"hexcode":"#973c0d","hsl":[20,84,32],"category":"orange","tints":["#32180b","#622a0f","#973c0d","#c94c0d","#f55f14"]},{"hexcode":"#46cceb","hsl":[191,80,60],"category":"blue","tints":["#298da3","#26b8d9","#46cceb","#6edef7","#99ecff"]},{"hexcode":"#a967db","hsl":[274,62,63],"category":"purple","tints":["#74409c","#8f49c5","#a967db","#c189ec","#d8b0f7"]},{"hexcode":"#f871e5","hsl":[308,91,71],"category":"purple","tints":["#db29c3","#ec4bd7","#f871e5","#fda1f0","#ffd1f9"]},{"hexcode":"#73f87d","hsl":[125,90,71],"category":"green","tints":["#2bda39","#4ceb59","#73f87d","#a1fda8","#d1ffd5"]},{"hexcode":"#4fdf27","hsl":[107,74,51],"category":"green","tints":["#377a24","#43ab26","#4fdf27","#6cef48","#8efb70"]},{"hexcode":"#b155e2","hsl":[279,71,61],"category":"purple","tints":["#79339e","#9936ce","#b155e2","#c779f1","#dca2fb"]},{"hexcode":"#ab11a6","hsl":[302,82,37],"category":"purple","tints":["#461044","#761373","#ab11a6","#df11d8","#f42fed"]},{"hexcode":"#dee566","hsl":[63,71,65],"category":"green","tints":["#a7ad38","#cbd246","#dee566","#eef38c","#f8fcb6"]},{"hexcode":"#779c6c","hsl":[106,20,52],"category":"green","tints":["#525252","#657660","#779c6c","#8fbb81","#a8d49b"]},{"hexcode":"#487255","hsl":[139,23,36],"category":"green","tints":["#282a28","#3a4b3f","#487255","#4f9c67","#5fbf7d"]},{"hexcode":"#ce9fe6","hsl":[280,59,76],"category":"purple","tints":["#9d63bb","#b67ed3","#ce9fe6","#e4c3f4","#f7edfd"]},{"hexcode":"#3de2b5","hsl":[164,74,56],"category":"green","tints":["#2a8d73","#2ac098","#3de2b5","#5ff1ca","#88fbdd"]},{"hexcode":"#b1583a","hsl":[15,51,46],"category":"red","tints":["#57382e","#814936","#b1583a","#d36d4a","#e68a6b"]},{"hexcode":"#a26523","hsl":[31,64,39],"category":"orange","tints":["#46311b","#724b22","#a26523","#d98020","#ee993f"]},{"hexcode":"#d0df87","hsl":[70,58,70],"category":"green","tints":["#a0b04f","#baca68","#d0df87","#e3efa9","#f3f9d2"]},{"hexcode":"#e077f6","hsl":[290,88,72],"category":"purple","tints":["#bc31d8","#d053ea","#e077f6","#eda7fb","#f7d7fe"]},{"hexcode":"#6c9541","hsl":[89,39,42],"category":"green","tints":["#38432d","#52693a","#6c9541","#87c149","#a0d765"]},{"hexcode":"#172f5d","hsl":[219,60,23],"category":"blue","tints":["#05070b","#111c32","#172f5d","#19428f","#1653c5"]},{"hexcode":"#7ecf43","hsl":[95,59,54],"category":"green","tints":["#517935","#67a739","#7ecf43","#99e364","#b4f188"]},{"hexcode":"#4b4fd7","hsl":[238,64,57],"category":"blue","tints":["#353888","#373bb9","#4b4fd7","#6d71e9","#9396f6"]},{"hexcode":"#ecf919","hsl":[63,95,54],"category":"green","tints":["#919816","#c6d011","#ecf919","#f3fc4a","#f8fe7b"]},{"hexcode":"#38d760","hsl":[135,67,53],"category":"green","tints":["#2d7c40","#2fac4e","#38d760","#58e97c","#7ef69c"]},{"hexcode":"#158ca0","hsl":[189,77,35],"category":"blue","tints":["#10363c","#155e6a","#158ca0","#0fb9d7","#1ddafc"]},{"hexcode":"#702b40","hsl":[342,45,30],"category":"red","tints":["#201317","#45212c","#702b40","#9e2e50","#d22d5e"]},{"hexcode":"#cca085","hsl":[23,41,66],"category":"orange","tints":["#8e705d","#b2876c","#cca085","#e1bba3","#f1d6c6"]},{"hexcode":"#c799df","hsl":[279,52,74],"category":"purple","tints":["#9564af","#af7dca","#c799df","#debdef","#f3e5fb"]},{"hexcode":"#7c39bd","hsl":[270,54,48],"category":"purple","tints":["#472f60","#61368c","#7c39bd","#944fd8","#ad71ea"]},{"hexcode":"#209e0e","hsl":[113,84,34],"category":"green","tints":["#123b0d","#1a6a10","#209e0e","#25d30d","#37f61e"]},{"hexcode":"#4a3ba1","hsl":[249,46,43],"category":"blue","tints":["#302b4a","#3f3672","#4a3ba1","#5844ca","#7562df"]},{"hexcode":"#52a558","hsl":[124,34,48],"category":"green","tints":["#3d513f","#4a784d","#52a558","#65c36b","#81d987"]},{"hexcode":"#3b9f9c","hsl":[178,46,43],"category":"blue","tints":["#2b4a49","#367270","#3b9f9c","#44cac6","#62dfdb"]},{"hexcode":"#f7082e","hsl":[350,94,50],"category":"red","tints":["#851427","#bc102d","#f7082e","#fc3657","#ff6680"]},{"hexcode":"#6a10b6","hsl":[273,84,39],"category":"purple","tints":["#34114f","#4f1381","#6a10b6","#880feb","#a036f7"]},{"hexcode":"#355787","hsl":[215,44,37],"category":"blue","tints":["#212a36","#2d415c","#355787","#376db9","#4b86d8"]},{"hexcode":"#9844ae","hsl":[288,44,47],"category":"purple","tints":["#4f3455","#723e7e","#9844ae","#b556cd","#cb75e1"]},{"hexcode":"#991e4a","hsl":[339,67,36],"category":"red","tints":["#3c1623","#681d37","#991e4a","#d01b5a","#f02d72"]},{"hexcode":"#0d97be","hsl":[193,87,40],"category":"blue","tints":["#114655","#126e87","#0d97be","#0dc1f2","#3acff8"]},{"hexcode":"#11264c","hsl":[219,63,18],"category":"blue","tints":["#0f1624","#111e37","#11264c","#13387c","#1049b1"]},{"hexcode":"#23c3fa","hsl":[195,96,56],"category":"blue","tints":["#167fa2","#10a8da","#23c3fa","#53d3fd","#85e0ff"]},{"hexcode":"#b1acf0","hsl":[244,69,81],"category":"blue","tints":["#716bcc","#8f89e1","#b1acf0","#bfbbf7","#cdcafc"]},{"hexcode":"#fe7d88","hsl":[355,98,74],"category":"red","tints":["#e52e3d","#f45260","#fe7d88","#ffaeb5","#ffe0e3"]},{"hexcode":"#7a4860","hsl":[331,26,38],"category":"red","tints":["#312b2e","#533c47","#7a4860","#a64e79","#c56392"]},{"hexcode":"#3e5958","hsl":[178,18,30],"category":"blue","tints":["#171c1c","#2c3a3a","#3e5958","#498381","#4fb0ad"]},{"hexcode":"#605b5a","hsl":[10,3,36],"category":"grey","tints":["#292928","#444141","#605b5a","#856b66","#a97e75"]},{"hexcode":"#e58913","hsl":[34,85,49],"category":"orange","tints":["#7a501a","#ae6d19","#e58913","#f2a33a","#f8ba68"]},{"hexcode":"#803524","hsl":[11,56,32],"category":"red","tints":["#2a1814","#52281e","#803524","#b23e24","#e24a28"]},{"hexcode":"#68da3a","hsl":[103,68,54],"category":"green","tints":["#45802d","#54b12f","#68da3a","#84eb5c","#a3f782"]},{"hexcode":"#3d2a99","hsl":[250,57,38],"category":"blue","tints":["#231d3f","#312669","#3d2a99","#4428cc","#5d41e6"]},{"hexcode":"#4876ac","hsl":[212,41,48],"category":"blue","tints":["#384656","#435f7f","#4876ac","#5d90cb","#7caadf"]},{"hexcode":"#2e319d","hsl":[238,55,40],"category":"blue","tints":["#212245","#2a2c6f","#2e319d","#2d32d2","#4c52e6"]},{"hexcode":"#11a201","hsl":[114,99,32],"category":"green","tints":["#0b3706","#106a06","#11a201","#16d501","#24fe0b"]},{"hexcode":"#8942ca","hsl":[271,56,53],"category":"purple","tints":["#553672","#6f3ba0","#8942ca","#a362df","#bc86ee"]},{"hexcode":"#a45102","hsl":[29,98,33],"category":"orange","tints":["#3b2007","#6e3907","#a45102","#da6a01","#ff830f"]},{"hexcode":"#432cdd","hsl":[248,72,52],"category":"blue","tints":["#32277c","#3a29ae","#432cdd","#644fee","#8776f9"]},{"hexcode":"#29b016","hsl":[113,78,39],"category":"green","tints":["#1b4d14","#237c18","#29b016","#29eb0f","#48fd30"]},{"hexcode":"#d0b1c5","hsl":[321,25,75],"category":"red","tints":["#92878e","#b398aa","#d0b1c5","#e6cbdd","#f8edf4"]},{"hexcode":"#2f4a03","hsl":[83,92,15],"category":"green","tints":["#1b2706","#243806","#2f4a03","#4e7d03","#6eb300"]},{"hexcode":"#afa7f1","hsl":[246,73,80],"category":"blue","tints":["#6e63cf","#8c82e3","#afa7f1","#d5d0fb","#ffffff"]}]